{
  "aluno-1": {
    "nome": "",
    "email-insper": "",
    "user-github": ""
  },
  "aluno-2": {
    "nome": "",
    "email-insper": "",
    "user-github": ""
  },
  "aluno-3": {
    "nome": "",
    "email-insper": "",
    "user-github": ""
  },
  "aluno-4": {
    "nome": "",
    "email-insper": "",
    "user-github": ""
  },
  "aluno-5": {
    "nome": "Ricardo Ribeiro Rodrigues",
    "email-insper": "ricardorr7@al.insper.edu.br",
    "user-github": "RicardoRibeiroRodrigues"
  },
  "aluno-6": {
    "nome": "",
    "email-insper": "",
    "user-github": ""
  }
}
